textdivider/__init__.py
textdivider-0.2.1.dist-info/METADATA
textdivider-0.2.1.dist-info/WHEEL
textdivider-0.2.1.dist-info/top_level.txt
textdivider-0.2.1.dist-info/RECORD
