Metadata-Version: 2.4
Name: textdivider
Version: 0.2.1
Summary: Split long text into parts without breaking words
Author-email: Jean Caiza <caiza58@gmail.com>
License-Expression: MIT
Keywords: text,split,word,chunk,string,divide
Requires-Python: >=3.7
